{
  "A": 0,
  "ARM": 1,
  "B": 2,
  "BABY": 3,
  "BAD": 4,
  "BED": 5,
  "BIG": 6,
  "BODY": 7,
  "BOOK": 8,
  "BOY": 9,
  "BOYFRIEND": 10,
  "BROTHER": 11,
  "BUT": 12,
  "C": 13,
  "CHAIR": 14,
  "CHILD": 15,
  "COLD": 16,
  "D": 17,
  "DO": 18,
  "DOCTOR": 19,
  "E": 20,
  "EAR": 21,
  "EYE": 22,
  "F": 23,
  "FAST": 24,
  "FRIEND": 25,
  "G": 26,
  "GIRLFRIEND": 27,
  "GO": 28,
  "H": 29,
  "HAND": 30,
  "HEAD": 31,
  "HELLO": 32,
  "HELP": 33,
  "HOLIDAY": 34,
  "HOME": 35,
  "HOT": 36,
  "HOUSE": 37,
  "I": 38,
  "IF": 39,
  "IT": 40,
  "J": 41,
  "K": 42,
  "L": 43,
  "LATER": 44,
  "LEG": 45,
  "LIKE": 46,
  "LISTEN": 47,
  "LOOK": 48,
  "LOVE": 49,
  "M": 50,
  "MAN": 51,
  "ME": 52,
  "MOUTH": 53,
  "MUM": 54,
  "MUST": 55,
  "N": 56,
  "NEED": 57,
  "NEW": 58,
  "NIGHT": 59,
  "NO": 60,
  "NOW": 61,
  "NURSE": 62,
  "P": 63,
  "PERSON": 64,
  "PLAY": 65,
  "POISON": 66,
  "R": 67,
  "S": 68,
  "SAD": 69,
  "SAME": 70,
  "SCHOOL": 71,
  "SEE": 72,
  "SHOP": 73,
  "SHOULD": 74,
  "SICK": 75,
  "SISTER": 76,
  "SIT": 77,
  "SMALL": 78,
  "SOON": 79,
  "STAND": 80,
  "STOP": 81,
  "STRONG": 82,
  "STUDENT": 83,
  "T": 84,
  "TALK": 85,
  "TEACHER": 86,
  "THEY": 87,
  "THINK": 88,
  "TIRED": 89,
  "TOMORROW": 90,
  "TOOTH": 91,
  "U": 92,
  "V": 93,
  "W": 94,
  "WAIT": 95,
  "WE": 96,
  "WEEK": 97,
  "WHAT": 98,
  "WHEN": 99,
  "WHO": 100,
  "WHY": 101,
  "WORK": 102,
  "WRITE": 103,
  "X": 104,
  "Y": 105,
  "YEAR": 106,
  "YOU": 107,
  "Z": 108
}